setup.py
pYVKApi.egg-info/PKG-INFO
pYVKApi.egg-info/SOURCES.txt
pYVKApi.egg-info/dependency_links.txt
pYVKApi.egg-info/top_level.txt
pyVK/__init__.py
pyVK/exceptions.py