Metadata-Version: 1.0
Name: pYVKApi
Version: 1.0.0
Summary: Пакет для работы с API vk.com
Home-page: https://github.com/Mereng/pyVKApi
Author: Mereng
Author-email: vladislav-sedov@yandex.ru
License: GPL3
Keywords: vk api vk.com vkontakte вк вконтакте
Platform: UNKNOWN
